dbt_duckdb_kedro_datasets/__init__.py
dbt_duckdb_kedro_datasets/ddkd.py
dbt_duckdb_kedro_datasets-0.1.2.dist-info/METADATA
dbt_duckdb_kedro_datasets-0.1.2.dist-info/WHEEL
dbt_duckdb_kedro_datasets-0.1.2.dist-info/RECORD
