Metadata-Version: 2.1
Name: dbt_duckdb_kedro_datasets
Version: 0.1.2
Summary: Combine duckdb-dbt and Kedro Dataset to easily read Kedro Dataset configs (yaml), enabling conversion of Kedro projects to dbt.
Author: Conrad
Author-email: conradbez1@gmail.com
Requires-Python: >=3.11,<4.0
Classifier: Programming Language :: Python :: 3
Classifier: Programming Language :: Python :: 3.11
Classifier: Programming Language :: Python :: 3.12
Requires-Dist: dbt-duckdb (>=1.8.0,<2.0.0)
Requires-Dist: fastparquet (>=2024.2.0,<2025.0.0)
Requires-Dist: kedro-datasets[pandas] (>=3.0.0,<4.0.0)
Requires-Dist: pandas (>=2.2.2,<3.0.0)
